dbdicom/__init__.py
dbdicom/api.py
dbdicom/const.py
dbdicom/database.py
dbdicom/dataset.py
dbdicom/dbd.py
dbdicom/register.py
dbdicom/external/__init__.py
dbdicom/external/__pycache__/__init__.cpython-311.pyc
dbdicom/external/dcm4che/README.md
dbdicom/external/dcm4che/__init__.py
dbdicom/external/dcm4che/__pycache__/__init__.cpython-311.pyc
dbdicom/external/dcm4che/bin/__init__.py
dbdicom/external/dcm4che/bin/deidentify
dbdicom/external/dcm4che/bin/deidentify.bat
dbdicom/external/dcm4che/bin/emf2sf
dbdicom/external/dcm4che/bin/emf2sf.bat
dbdicom/external/dcm4che/bin/__pycache__/__init__.cpython-311.pyc
dbdicom/external/dcm4che/etc/__init__.py
dbdicom/external/dcm4che/etc/emf2sf/__init__.py
dbdicom/external/dcm4che/etc/emf2sf/log4j.properties
dbdicom/external/dcm4che/lib/__init__.py
dbdicom/external/dcm4che/lib/commons-cli-1.4.jar
dbdicom/external/dcm4che/lib/dcm4che-core-5.23.1.jar
dbdicom/external/dcm4che/lib/dcm4che-emf-5.23.1.jar
dbdicom/external/dcm4che/lib/dcm4che-tool-common-5.23.1.jar
dbdicom/external/dcm4che/lib/dcm4che-tool-emf2sf-5.23.1.jar
dbdicom/external/dcm4che/lib/log4j-1.2.17.jar
dbdicom/external/dcm4che/lib/slf4j-api-1.7.30.jar
dbdicom/external/dcm4che/lib/slf4j-log4j12-1.7.30.jar
dbdicom/external/dcm4che/lib/macosx-x86-64/libopencv_java.jnilib
dbdicom/external/dcm4che/lib/windows-x86/clib_jiio.dll
dbdicom/external/dcm4che/lib/windows-x86/clib_jiio_sse2.dll
dbdicom/external/dcm4che/lib/windows-x86/clib_jiio_util.dll
dbdicom/external/dcm4che/lib/windows-x86/opencv_java.dll
dbdicom/external/dcm4che/lib/windows-x86-64/opencv_java.dll
dbdicom/sop_classes/ct_image.py
dbdicom/sop_classes/enhanced_mr_image.py
dbdicom/sop_classes/mr_image.py
dbdicom/sop_classes/parametric_map.py
dbdicom/sop_classes/secondary_capture.py
dbdicom/sop_classes/segmentation.py
dbdicom/sop_classes/ultrasound_multiframe_image.py
dbdicom/sop_classes/xray_angiographic_image.py
dbdicom/utils/dcm4che.py
dbdicom/utils/image.py
dbdicom/utils/points.py
dbdicom/utils/pydicom_dataset.py
dbdicom-0.3.19.dist-info/licenses/LICENSE
dbdicom-0.3.19.dist-info/METADATA
dbdicom-0.3.19.dist-info/WHEEL
dbdicom-0.3.19.dist-info/top_level.txt
dbdicom-0.3.19.dist-info/RECORD
