Metadata-Version: 2.4
Name: dbdicom
Version: 0.3.19
Summary: A pythonic interface for reading and writing DICOM databases
Author-email: Steven Sourbron <s.sourbron@sheffield.ac.uk>, Ebony Gunwhy <e.gunwhy@sheffield.ac.uk>
Project-URL: Homepage, https://openmiblab.github.io/dbdicom/
Keywords: python,medical imaging,DICOM
Classifier: Development Status :: 3 - Alpha
Classifier: Intended Audience :: Developers
Classifier: Intended Audience :: Science/Research
Classifier: Topic :: Scientific/Engineering
Classifier: Environment :: Console
Classifier: Operating System :: OS Independent
Classifier: License :: OSI Approved :: Apache Software License
Classifier: Programming Language :: Python
Classifier: Programming Language :: Python :: 3
Requires-Python: >=3.6
License-File: LICENSE
Requires-Dist: tqdm
Requires-Dist: importlib-resources
Requires-Dist: numpy
Requires-Dist: pandas
Requires-Dist: vreg
Requires-Dist: pydicom>=3.0
Dynamic: license-file
